[
  {
    "name": "c-card-1",
    "title": "Basic card",
    "description": "Basic card",
    "order": 1
  },
  {
    "name": "c-card-2",
    "title": "Card header with border",
    "description": "Card header with border",
    "order": 2
  },
  {
    "name": "c-card-3",
    "title": "Card with border separation",
    "description": "Card with border separation",
    "order": 3
  },
  {
    "name": "c-card-4",
    "title": "Card with header and footer",
    "description": "Card with header and footer",
    "order": 4
  },
  {
    "name": "c-card-5",
    "title": "Card with link",
    "description": "Card with link",
    "order": 5
  },
  {
    "name": "c-card-6",
    "title": "Card with dropdown menu",
    "description": "Card with dropdown menu",
    "order": 6
  },
  {
    "name": "c-card-7",
    "title": "Card with image",
    "description": "Card with image",
    "order": 7
  },
  {
    "name": "c-card-8",
    "title": "Card with image scale hover effect",
    "description": "Card with image scale hover effect",
    "order": 8
  },
  {
    "name": "c-card-9",
    "title": "Card with full image",
    "description": "Card with full image",
    "order": 9
  },
  {
    "name": "c-card-10",
    "title": "Full card with image and shadow fade effect",
    "description": "Full card with image and shadow fade effect",
    "order": 10
  },
  {
    "name": "c-card-11",
    "title": "Card with stacked depth effect",
    "description": "Card with stacked depth effect",
    "order": 11
  },
  {
    "name": "c-card-12",
    "title": "Advanced clean login form card",
    "description": "Advanced clean login form card",
    "order": 12
  },
  {
    "name": "c-card-13",
    "title": "Expandable billing usage card",
    "description": "Expandable billing usage card",
    "order": 13
  },
  {
    "name": "c-card-14",
    "title": "Deployment status summary card",
    "description": "Deployment status summary card",
    "order": 14
  },
  {
    "name": "c-card-15",
    "title": "Stat card with trend and overflow menu",
    "description": "Stat card with trend and overflow menu",
    "order": 15
  },
  {
    "name": "c-card-16",
    "title": "Card with header badge and actions",
    "description": "Card with header badge and actions",
    "order": 16
  },
  {
    "name": "c-card-17",
    "title": "Card with icon, title and link",
    "description": "Card with icon, title and link",
    "order": 17
  },
  {
    "name": "c-card-18",
    "title": "Card with header label and link",
    "description": "Card with header label and link",
    "order": 18
  }
]
